pydrobert/param/__init__.py
pydrobert/param/_classic_argparse.py
pydrobert/param/_classic_serialization.py
pydrobert/param/_file_serialization.py
pydrobert/param/_serializer.py
pydrobert/param/_version.py
pydrobert/param/abc.py
pydrobert/param/argparse.py
pydrobert/param/command_line.py
pydrobert/param/config.py
pydrobert/param/optuna.py
pydrobert/param/serialization.py
pydrobert_param-0.4.1.dist-info/LICENSE
pydrobert_param-0.4.1.dist-info/METADATA
pydrobert_param-0.4.1.dist-info/WHEEL
pydrobert_param-0.4.1.dist-info/entry_points.txt
pydrobert_param-0.4.1.dist-info/top_level.txt
pydrobert_param-0.4.1.dist-info/RECORD
