Metadata-Version: 2.1
Name: pydrobert-param
Version: 0.4.1
Summary: Utilities for the python package 'param'
Home-page: https://github.com/sdrobert/pydrobert-param
Author: Sean Robertson
Author-email: sdrobert@cs.toronto.edu
License: Apache-2.0
Project-URL: Documentation, https://pydrobert-param.readthedocs.io
Classifier: Development Status :: 3 - Alpha
Classifier: License :: OSI Approved :: Apache Software License
Classifier: Programming Language :: Python :: 3
Requires-Python: >=3.7
License-File: LICENSE
Requires-Dist: param >=1.12
Provides-Extra: all
Requires-Dist: ruamel.yaml >=0.15 ; extra == 'all'
Requires-Dist: optuna ; extra == 'all'
Requires-Dist: numpy ; extra == 'all'
Requires-Dist: pandas ; extra == 'all'
Provides-Extra: optuna
Requires-Dist: optuna ; extra == 'optuna'
Provides-Extra: types
Requires-Dist: numpy ; extra == 'types'
Requires-Dist: pandas ; extra == 'types'
Provides-Extra: yaml
Requires-Dist: ruamel.yaml >=0.15 ; extra == 'yaml'
